{"cameraMode":{"drawMode":0,"name":"Shaded","section":"Shading Mode"},"sceneLighting":false,"audioPlay":false,"sceneViewState":{"m_AlwaysRefresh":false,"showFog":true,"showSkybox":false,"showFlares":true,"showImageEffects":true,"showParticleSystems":true,"showVisualEffectGraphs":true,"m_FxEnabled":true},"in2DMode":false,"pivot":{"x":0.13552875816822053,"y":1.6010428667068482,"z":3.111539840698242},"rotation":{"x":0.000009495430276729167,"y":0.027908509597182275,"z":-0.000007593019745399943,"w":0.9996235966682434},"size":4.0691328048706059,"orthographic":false}